simple_file_logger/__init__.py
simple_file_logger/simple_logger.py
simple_file_logger-0.1.6.dist-info/LICENSE
simple_file_logger-0.1.6.dist-info/WHEEL
simple_file_logger-0.1.6.dist-info/METADATA
simple_file_logger-0.1.6.dist-info/RECORD
