Metadata-Version: 2.1
Name: simple-file-logger
Version: 0.1.6
Summary: A simple logger class to log to files
Home-page: https://github.com/karanveersp/simple-file-logger
License: MIT
Author: Karanveer Singh
Author-email: karan_4496@hotmail.com
Requires-Python: >=3.7,<4.0
Classifier: License :: OSI Approved :: MIT License
Classifier: Programming Language :: Python :: 3
Classifier: Programming Language :: Python :: 3.10
Classifier: Programming Language :: Python :: 3.7
Classifier: Programming Language :: Python :: 3.8
Classifier: Programming Language :: Python :: 3.9
Project-URL: Repository, https://github.com/karanveersp/simple-file-logger
